{
	"info": {
		"_postman_id": "44efa00e-ddb9-440d-9c4b-f7ef002d2b60",
		"name": "candidate-service",
		"schema": "https://schema.getpostman.com/json/collection/v2.1.0/collection.json",
		"_exporter_id": "29421585"
	},
	"item": [
		{
			"name": "http://localhost:8090/api/candidates - create",
			"request": {
				"method": "POST",
				"header": [
					{
						"key": "Accept",
						"value": "application/json",
						"type": "text"
					},
					{
						"key": "Content-Type",
						"value": "application/json",
						"type": "text"
					}
				],
				"body": {
					"mode": "raw",
					"raw": "{\r\n    \"basicInfo\": {\r\n        \"firstName\": \"Kotaiah\",\r\n        \"lastName\": \"Nalleboina\",\r\n        \"gender\": \"male\",\r\n        \"email\": \"kotaiahnalleboina@gmail.com\",\r\n        \"phone\": \"9381515362\",\r\n        \"candidateNationality\": \"india\",\r\n        \"currentLocation\": \"guntur\",\r\n        \"visaStatus\": \"accepted\",\r\n        \"languageKnown\": \"Telugu,English\",\r\n        \"candidateOwner\": \"avensys\"\r\n    },\r\n    \"professionalInfo\": {\r\n        \"totalExperience\": \"2.1\",\r\n        \"relevantExperience\": \"1.8\",\r\n        \"currentEmployer\": \"avensys\",\r\n        \"currentPositionTitle\": \"softwareEngineer\",\r\n        \"candidateCurrentSalary\": \"600000\",\r\n        \"candidateExpectedSalary\": \"780000\",\r\n        \"reasonForChange\": \"better Career Greoth\",\r\n        \"noticePeriod\": \"3.0\",\r\n        \"profileSummary\": \"softeareEngineer\",\r\n        \"primarySkills\": \"Java,Spring\",\r\n        \"secondarySkills\": \"HTML,CSS\",\r\n        \"additionalInfo\": \"SoftwareEngineer\",\r\n        \"candidateStatus\": \"Selected\",\r\n        \"source\": \"LinkedIn\",\r\n        \"referrersName\": \"SeemaVarma\",\r\n        \"emailOptOut\": true\r\n    }\r\n}",
					"options": {
						"raw": {
							"language": "json"
						}
					}
				},
				"url": {
					"raw": "http://localhost:8090/api/candidates",
					"protocol": "http",
					"host": [
						"localhost"
					],
					"port": "8090",
					"path": [
						"api",
						"candidates"
					]
				}
			},
			"response": []
		},
		{
			"name": "http://localhost:8090/api/candidates/1 - GET",
			"protocolProfileBehavior": {
				"disableBodyPruning": true
			},
			"request": {
				"method": "GET",
				"header": [
					{
						"key": "Accept",
						"value": "application/json",
						"type": "text"
					},
					{
						"key": "Content-Type",
						"value": "application/json",
						"type": "text"
					}
				],
				"body": {
					"mode": "raw",
					"raw": "",
					"options": {
						"raw": {
							"language": "json"
						}
					}
				},
				"url": {
					"raw": "http://localhost:8090/api/candidates/1",
					"protocol": "http",
					"host": [
						"localhost"
					],
					"port": "8090",
					"path": [
						"api",
						"candidates",
						"1"
					]
				}
			},
			"response": []
		},
		{
			"name": "http://localhost:8090/api/candidates - GET all",
			"protocolProfileBehavior": {
				"disableBodyPruning": true
			},
			"request": {
				"method": "GET",
				"header": [
					{
						"key": "Accept",
						"value": "application/json",
						"type": "text"
					},
					{
						"key": "Content-Type",
						"value": "application/json",
						"type": "text"
					}
				],
				"body": {
					"mode": "raw",
					"raw": "",
					"options": {
						"raw": {
							"language": "json"
						}
					}
				},
				"url": {
					"raw": "http://localhost:8090/api/candidates",
					"protocol": "http",
					"host": [
						"localhost"
					],
					"port": "8090",
					"path": [
						"api",
						"candidates"
					]
				}
			},
			"response": []
		},
		{
			"name": "http://localhost:8090/api/candidates/1 - PUT",
			"request": {
				"method": "PUT",
				"header": [],
				"body": {
					"mode": "raw",
					"raw": "{\r\n    \"basicInfo\": {\r\n        \"firstName\": \"kotaiah\",\r\n        \"lastName\": \"nalleboina\",\r\n        \"gender\": \"male\",\r\n        \"email\": \"kotaiahnalleboina@gmail.com\",\r\n        \"phone\": \"9381515362\",\r\n        \"candidateNationality\": \"india\",\r\n        \"currentLocation\": \"guntur\",\r\n        \"visaStatus\": \"accepted\",\r\n        \"languageKnown\": \"TeluguEnglish\",\r\n        \"candidateOwner\": \"avensys\"\r\n    },\r\n    \"professionalInfo\": {\r\n        \"totalExperience\": \"2.1\",\r\n        \"relevantExperience\": \"1.8\",\r\n        \"currentEmployer\": \"avensys\",\r\n        \"currentPositionTitle\": \"softwareEngineer\",\r\n        \"candidateCurrentSalary\": \"600000\",\r\n        \"candidateExpectedSalary\": \"780000\",\r\n        \"reasonForChange\": \"betterCareerGreoth\",\r\n        \"noticePeriod\": \"3.0\",\r\n        \"profileSummary\": \"softeareEngineer\",\r\n        \"primarySkills\": \"Java,Spring\",\r\n        \"secondarySkills\": \"HTMLCSS\",\r\n        \"additionalInfo\": \"SoftwareEngineer\",\r\n        \"candidateStatus\": \"Selected\",\r\n        \"source\": \"LinkedIn\",\r\n        \"referrer'sName\": \"SeemaVarma\",\r\n        \"emailOptOut\": false\r\n    }\r\n}",
					"options": {
						"raw": {
							"language": "json"
						}
					}
				},
				"url": {
					"raw": "http://localhost:8090/api/candidates/1",
					"protocol": "http",
					"host": [
						"localhost"
					],
					"port": "8090",
					"path": [
						"api",
						"candidates",
						"1"
					]
				}
			},
			"response": []
		},
		{
			"name": "http://localhost:8090/api/candidate/1 - delete",
			"request": {
				"method": "DELETE",
				"header": [],
				"body": {
					"mode": "raw",
					"raw": "",
					"options": {
						"raw": {
							"language": "json"
						}
					}
				},
				"url": {
					"raw": "http://localhost:8090/api/candidates1",
					"protocol": "http",
					"host": [
						"localhost"
					],
					"port": "8090",
					"path": [
						"api",
						"candidates1"
					]
				}
			},
			"response": []
		}
	]
}